pyhfs/__init__.py
pyhfs/client.py
pyhfs/exception.py
pyhfs/session.py
pyhfs/tests/__init__.py
pyhfs/tests/mock_session.py
pyhfs/tests/test_client.py
pyhfs/tests/test_mock_client.py
pyhfs/tests/test_session.py
pyhfs/tests/utils.py
pyhfs/tests/data/getAlarmList.json
pyhfs/tests/data/getKpiStationDay.json
pyhfs/tests/data/getKpiStationHour.json
pyhfs/tests/data/getKpiStationMonth.json
pyhfs/tests/data/getKpiStationYear.json
pyhfs/tests/data/getStationRealKpi.json
pyhfs/tests/data/stations.json
pyhfs-0.1.1.dist-info/METADATA
pyhfs-0.1.1.dist-info/WHEEL
pyhfs-0.1.1.dist-info/licenses/LICENSE
pyhfs-0.1.1.dist-info/RECORD
