Metadata-Version: 2.1
Name: pyhfs
Version: 0.1.1
Summary: Python client for Huawei FusionSolar SmartPVMS Northbound Interface
Project-URL: Homepage, https://github.com/guillaumeblanc/pyhfs
Project-URL: Bug Tracker, https://github.com/guillaumeblanc/pyhfs/issues
Author-email: Guillaume Blanc <guillaumeblanc.sc@gmail.com>
License-File: LICENSE
Classifier: License :: OSI Approved :: MIT License
Classifier: Operating System :: OS Independent
Classifier: Programming Language :: Python :: 3
Requires-Python: >=3.7
